scdl/__init__.py
scdl/client.py
scdl/scdl.py
scdl/utils.py
scdlpy-1.6.1.dist-info/DESCRIPTION.rst
scdlpy-1.6.1.dist-info/METADATA
scdlpy-1.6.1.dist-info/RECORD
scdlpy-1.6.1.dist-info/WHEEL
scdlpy-1.6.1.dist-info/entry_points.txt
scdlpy-1.6.1.dist-info/metadata.json
scdlpy-1.6.1.dist-info/top_level.txt
