Metadata-Version: 2.0
Name: scdlpy
Version: 1.6.1
Summary: Download Music from Souncloud
Home-page: https://bitbucket.org/DarkArtek/scdl
Author: DarkArtek
Author-email: artek@ahsubs-design.com
License: UNKNOWN
Platform: UNKNOWN
Classifier: Programming Language :: Python
Classifier: Development Status :: 5 - Production/Stable
Classifier: License :: OSI Approved :: GNU General Public License v2 (GPLv2)
Classifier: Operating System :: OS Independent
Classifier: Programming Language :: Python :: 3.4
Classifier: Topic :: Internet
Classifier: Topic :: Multimedia :: Sound/Audio
Requires-Dist: clint
Requires-Dist: docopt
Requires-Dist: mutagen
Requires-Dist: requests
Requires-Dist: termcolor
